[
  {
    "input_path": "https://raw.githubusercontent.com/rubenlier/rubenlier.github.io/master/headlines_latest.jsonl?nocache=1784542813",
    "n_items": 2538,
    "n_clusters": 1985,
    "created_at_utc": "2026-07-20T10:35:08Z",
    "clusters": [
      {
        "score": 315.8602657624965,
        "size": 78,
        "n_sources": 57,
        "n_continents": 10,
        "continents": [
          "Africa",
          "China",
          "East Asia",
          "Europe East",
          "Europe North",
          "Europe South",
          "Middle East",
          "North America",
          "South America",
          "South Asia"
        ],
        "coherence": 0.7819327116012573,
        "title": "Spain wins the World Cup by beating Argentina 1-0 in extra time",
        "central_article": {
          "title": "Spain wins the World Cup by beating Argentina 1-0 in extra time",
          "url": "https://apnews.com/article/argentina-spain-world-cup-final-score-messi-fccc26aa12d9226e63d06b601b770617",
          "source_id": "apnews.com",
          "continent": "North America",
          "published_at": null,
          "scraped_at_utc": "2026-07-20T09:51:29.178891+00:00"
        },
        "members_preview": []
      },
      {
        "score": 204.36965471328415,
        "size": 58,
        "n_sources": 36,
        "n_continents": 11,
        "continents": [
          "Africa",
          "China",
          "East Asia",
          "Europe East",
          "Europe North",
          "Europe South",
          "Middle East",
          "North America",
          "Oceania",
          "South America",
          "South Asia"
        ],
        "coherence": 0.7677032351493835,
        "title": "US carries out another round of air strikes on Iran after death of soldier",
        "central_article": {
          "title": "US carries out another round of air strikes on Iran after death of soldier",
          "url": "https://www.irishtimes.com/world/middle-east/2026/07/20/us-carries-out-another-round-of-air-strikes-on-iran-after-death-of-soldier/",
          "source_id": "irishtimes.com",
          "continent": "Europe North",
          "published_at": null,
          "scraped_at_utc": "2026-07-20T09:49:16.614591+00:00"
        },
        "members_preview": []
      },
      {
        "score": 123.50713842237641,
        "size": 30,
        "n_sources": 25,
        "n_continents": 8,
        "continents": [
          "Africa",
          "Europe East",
          "Europe North",
          "Europe South",
          "Middle East",
          "North America",
          "South America",
          "South Asia"
        ],
        "coherence": 0.8035963177680969,
        "title": "Andy Burnham to enter office as Britain’s new prime minister",
        "central_article": {
          "title": "Andy Burnham to enter office as Britain’s new prime minister",
          "url": "https://www.irishtimes.com/world/uk/2026/07/20/andy-burnham-downing-street-live-updates/",
          "source_id": "irishtimes.com",
          "continent": "Europe North",
          "published_at": null,
          "scraped_at_utc": "2026-07-20T09:49:16.614591+00:00"
        },
        "members_preview": []
      },
      {
        "score": 86.0799128810307,
        "size": 20,
        "n_sources": 18,
        "n_continents": 8,
        "continents": [
          "Africa",
          "China",
          "Europe East",
          "Europe North",
          "Europe South",
          "Oceania",
          "South America",
          "South Asia"
        ],
        "coherence": 0.7970925569534302,
        "title": "Célébration de la victoire de l’Espagne à la Coupe du monde : Donald Trump tente de s’immiscer sur la photo",
        "central_article": {
          "title": "Célébration de la victoire de l’Espagne à la Coupe du monde : Donald Trump tente de s’immiscer sur la photo",
          "url": "https://www.rtbf.be/article/celebration-de-la-victoire-de-l-espagne-a-la-coupe-du-monde-donald-trump-tente-de-s-immiscer-sur-la-photo-11760398",
          "source_id": "rtbf.be",
          "continent": "Europe South",
          "published_at": null,
          "scraped_at_utc": "2026-07-20T09:47:55.479585+00:00"
        },
        "members_preview": []
      },
      {
        "score": 62.9429096507696,
        "size": 19,
        "n_sources": 17,
        "n_continents": 6,
        "continents": [
          "China",
          "Europe East",
          "Europe North",
          "Europe South",
          "Middle East",
          "North America"
        ],
        "coherence": 0.8034510612487793,
        "title": "Ukraine targets Moscow with 400 drones after Russia attacked Kyiv",
        "central_article": {
          "title": "Ukraine targets Moscow with 400 drones after Russia attacked Kyiv",
          "url": "https://www.thetimes.com/world/russia-ukraine-war/article/ukraine-russia-war-news-latest-moscow-attack-q2pqcdf9c",
          "source_id": "thetimes.com",
          "continent": "Europe North",
          "published_at": null,
          "scraped_at_utc": "2026-07-20T09:46:40.934083+00:00"
        },
        "members_preview": []
      },
      {
        "score": 45.153130119802405,
        "size": 10,
        "n_sources": 10,
        "n_continents": 5,
        "continents": [
          "Europe East",
          "Europe North",
          "Europe South",
          "Middle East",
          "North America"
        ],
        "coherence": 0.8796073198318481,
        "title": "Hungary’s Prime Minister Magyar will ask chess champion Judit Polgar to be next president",
        "central_article": {
          "title": "Hungary’s Prime Minister Magyar will ask chess champion Judit Polgar to be next president",
          "url": "https://www.theglobeandmail.com/world/article-hungary-pm-magyar-president-chess-judit-polgar/",
          "source_id": "theglobeandmail.com",
          "continent": "North America",
          "published_at": null,
          "scraped_at_utc": "2026-07-20T09:49:02.400891+00:00"
        },
        "members_preview": []
      },
      {
        "score": 39.846173529652,
        "size": 7,
        "n_sources": 7,
        "n_continents": 6,
        "continents": [
          "East Asia",
          "Europe North",
          "Europe South",
          "Middle East",
          "Oceania",
          "South Asia"
        ],
        "coherence": 0.8894713521003723,
        "title": "Police cane supporters of India’s cockroach movement as thousands gather for march",
        "central_article": {
          "title": "Police cane supporters of India’s cockroach movement as thousands gather for march",
          "url": "https://kathmandupost.com/world/2026/07/20/police-cane-supporters-of-india-s-cockroach-movement-as-thousands-gather-for-march",
          "source_id": "kathmandupost.com",
          "continent": "South Asia",
          "published_at": null,
          "scraped_at_utc": "2026-07-20T09:52:49.155060+00:00"
        },
        "members_preview": []
      },
      {
        "score": 33.980628297383156,
        "size": 11,
        "n_sources": 11,
        "n_continents": 6,
        "continents": [
          "Africa",
          "East Asia",
          "Europe North",
          "Europe South",
          "Middle East",
          "North America"
        ],
        "coherence": 0.7672271728515625,
        "title": "Coupe du monde 2026 : les images fortes de Lionel Messi en larmes après le sacre de l’Espagne",
        "central_article": {
          "title": "Coupe du monde 2026 : les images fortes de Lionel Messi en larmes après le sacre de l’Espagne",
          "url": "https://www.rtbf.be/article/coupe-du-monde-2026-les-images-fortes-de-lionel-messi-en-larmes-apres-le-sacre-de-l-espagne-11760443",
          "source_id": "rtbf.be",
          "continent": "Europe South",
          "published_at": null,
          "scraped_at_utc": "2026-07-20T09:47:55.479585+00:00"
        },
        "members_preview": []
      },
      {
        "score": 31.912278580998144,
        "size": 8,
        "n_sources": 8,
        "n_continents": 5,
        "continents": [
          "Europe East",
          "Europe North",
          "North America",
          "Oceania",
          "South Asia"
        ],
        "coherence": 0.8548222780227661,
        "title": "Influencers Andrew and Tristan Tate arrested in US on new charges, face extradition",
        "central_article": {
          "title": "Influencers Andrew and Tristan Tate arrested in US on new charges, face extradition",
          "url": "https://www.sbs.com.au/news/article/influencers-andrew-and-tristan-tate-arrested-in-us-on-new-charges-face-extradition/6a5y4dd6a",
          "source_id": "sbs.com.au",
          "continent": "Oceania",
          "published_at": null,
          "scraped_at_utc": "2026-07-20T09:49:05.167702+00:00"
        },
        "members_preview": []
      },
      {
        "score": 24.783328417809496,
        "size": 7,
        "n_sources": 7,
        "n_continents": 5,
        "continents": [
          "Africa",
          "Europe East",
          "Europe South",
          "Middle East",
          "North America"
        ],
        "coherence": 0.8309646248817444,
        "title": "Christopher Nolan's 'The Odyssey' stuns with record opening weekend",
        "central_article": {
          "title": "Christopher Nolan's 'The Odyssey' stuns with record opening weekend",
          "url": "https://www.usatoday.com/story/entertainment/movies/2026/07/19/the-odyssey-box-office-opening-weekend-record/90926736007/",
          "source_id": "usatoday.com",
          "continent": "North America",
          "published_at": null,
          "scraped_at_utc": "2026-07-20T09:51:54.896208+00:00"
        },
        "members_preview": []
      }
    ]
  }
]